{
  "project_info": {
    "project_number": "272258701868",
    "project_id": "akaitracker-1402f",
    "storage_bucket": "akaitracker-1402f.appspot.com"
  },
  "client": [
    {
      "client_info": {
        "mobilesdk_app_id": "1:272258701868:android:9cfc434a642f760fdecf89",
        "android_client_info": {
          "package_name": "com.akaitracker"
        }
      },
      "oauth_client": [],
      "api_key": [
        {
          "current_key": "AIzaSyBmH9ay2AGKX6xxSEOZShQrpfAIwD30Qsk"
        }
      ],
      "services": {
        "appinvite_service": {
          "other_platform_oauth_client": []
        }
      }
    }
  ],
  "configuration_version": "1"
}